CHANGELOG.md
LICENSE
MANIFEST.in
README.md
setup.cfg
setup.py
tox.ini
ahoyhoy/__init__.py
ahoyhoy.egg-info/PKG-INFO
ahoyhoy.egg-info/SOURCES.txt
ahoyhoy.egg-info/dependency_links.txt
ahoyhoy.egg-info/requires.txt
ahoyhoy.egg-info/top_level.txt
ahoyhoy/circuit/__init__.py
ahoyhoy/circuit/circuit.py
ahoyhoy/classifiers/__init__.py
ahoyhoy/classifiers/exceptions.py
ahoyhoy/classifiers/servererror.py
ahoyhoy/client/__init__.py
ahoyhoy/client/builder.py
ahoyhoy/client/client.py
ahoyhoy/client/exceptions.py
ahoyhoy/endpoints/__init__.py
ahoyhoy/endpoints/endpoint.py
ahoyhoy/http/__init__.py
ahoyhoy/http/proxy.py
ahoyhoy/lb/__init__.py
ahoyhoy/lb/exceptions.py
ahoyhoy/lb/iloadbalancer.py
ahoyhoy/lb/randomlb.py
ahoyhoy/lb/roundrobinlb.py
ahoyhoy/lb/providers/__init__.py
ahoyhoy/lb/providers/iprovider.py
ahoyhoy/lb/providers/listprovider.py
ahoyhoy/retries/__init__.py
ahoyhoy/retries/retries.py
ahoyhoy/servicediscovery/__init__.py
ahoyhoy/servicediscovery/servicediscovery.py
ahoyhoy/utils/__init__.py
ahoyhoy/utils/django.py
ahoyhoy/utils/host.py
docs/PYPI_README.rst
docs/__init__.py
docs/general/Makefile
docs/general/__init__.py
docs/general/conf.py
docs/general/contents.rst
docs/general/index.rst
docs/general/_build/doctrees/contents.doctree
docs/general/_build/doctrees/environment.pickle
docs/general/_build/doctrees/index.doctree
docs/general/_build/doctrees/apis/api.doctree
docs/general/_build/doctrees/apis/base.doctree
docs/general/_build/doctrees/apis/circuit.doctree
docs/general/_build/doctrees/apis/client.doctree
docs/general/_build/doctrees/apis/endpoint.doctree
docs/general/_build/doctrees/apis/lb.doctree
docs/general/_build/doctrees/apis/proxy.doctree
docs/general/_build/doctrees/apis/retries.doctree
docs/general/_build/doctrees/apis/servicediscovery.doctree
docs/general/_build/doctrees/contents/advanced_usage.doctree
docs/general/_build/doctrees/contents/foreword.doctree
docs/general/_build/doctrees/contents/installation.doctree
docs/general/_build/doctrees/contents/objects_hierarchy.doctree
docs/general/_build/doctrees/contents/quickstart.doctree
docs/general/_build/doctrees/contents/testing.doctree
