Metadata-Version: 1.1
Name: ahoyhoy
Version: 4.0.2
Summary: Python client for service requests
Home-page: http://www.ncbi.nlm.nih.gov/
Author: NCBI
Author-email: python-core@ncbi.nlm.nih.gov
License: Public Domain
Keywords: python web requests client
Platform: UNKNOWN
Classifier: Intended Audience :: Developers
Classifier: License :: Public Domain
Classifier: Operating System :: OS Independent
Classifier: Programming Language :: Python
Classifier: Programming Language :: Python :: 2
Classifier: Programming Language :: Python :: 2.7
Classifier: Programming Language :: Python :: 3
Classifier: Programming Language :: Python :: 3.4
Classifier: Programming Language :: Python :: 3.5
Classifier: Topic :: Internet :: WWW/HTTP
Classifier: Topic :: Internet :: WWW/HTTP :: Dynamic Content
